causal_lasso/__init__.py
causal_lasso/general_weights_algo.py
causal_lasso/positive_weights_algo.py
causal_lasso/solver.py
graph_tools/__init__.py
graph_tools/data_gen.py
graph_tools/metrics.py
causal_lasso-1.0.1.dist-info/LICENSE
causal_lasso-1.0.1.dist-info/METADATA
causal_lasso-1.0.1.dist-info/WHEEL
causal_lasso-1.0.1.dist-info/top_level.txt
causal_lasso-1.0.1.dist-info/RECORD
