Metadata-Version: 2.1
Name: causal-lasso
Version: 1.0.1
Summary: Causal Lasso
Home-page: https://github.com/manon643/causal_lasso
Author: Manon Romain
Author-email: manon.romain@ens.fr
License: UNKNOWN
Platform: UNKNOWN
Classifier: Programming Language :: Python :: 3
Classifier: License :: OSI Approved :: MIT License
Classifier: Operating System :: OS Independent
Requires-Python: >=3.6
Requires-Dist: numpy
Requires-Dist: scipy
Requires-Dist: tqdm
Requires-Dist: networkx
Requires-Dist: Mosek
Requires-Dist: cvxpy
Requires-Dist: python-igraph
